MANIFEST.in
README.rst
setup.py
django_gevent_deploy/__init__.py
django_gevent_deploy/models.py
django_gevent_deploy/views.py
django_gevent_deploy.egg-info/PKG-INFO
django_gevent_deploy.egg-info/SOURCES.txt
django_gevent_deploy.egg-info/dependency_links.txt
django_gevent_deploy.egg-info/requires.txt
django_gevent_deploy.egg-info/top_level.txt
django_gevent_deploy/management/__init__.py
django_gevent_deploy/management/commands/__init__.py
django_gevent_deploy/management/commands/rungevent.py