Metadata-Version: 1.0
Name: django-gevent-deploy
Version: 1.0
Summary: Django manage.py hook for starting gevent's WSGI server
Home-page: https://github.com/miki725/django-gevent-deploy
Author: Miroslav Shubernetskiy
Author-email: miroslav@miki725.com
License: MIT
Keywords: django
Platform: UNKNOWN
Classifier: Development Status :: 3 - Alpha
Classifier: Framework :: Django
Classifier: Intended Audience :: Developers
Classifier: Operating System :: OS Independent
Classifier: Programming Language :: Python
Classifier: Topic :: Utilities
Classifier: License :: OSI Approved :: MIT License
